Workbook

Sheet Dashboard
A1: Daily + Rollup Dashboard
A3: Selected Date: | B3: 46029 | C3: (Change this date to view KPIs) | F3: Week Start: | G3: =IF($B$3="","",$B$3-WEEKDAY($B$3,2)+1) -> 46027
F4: Month Start: | G4: =IF($B$3="","",EOMONTH($B$3,-1)+1) -> 46023
A5: Daily KPIs
A6: Metric | B6: Actual | C6: Target | D6: Status
A7: Net Sales ($) | B7: =SUMIFS('Daily Ops'!$H$2:$H$401,'Daily Ops'!$A$2:$A$401,$B$3) -> 0
A8: Food Sales ($) | B8: =SUMIFS('Daily Ops'!$I$2:$I$401,'Daily Ops'!$A$2:$A$401,$B$3) -> 0
A9: Alcohol Sales ($) | B9: =SUMIFS('Daily Ops'!$J$2:$J$401,'Daily Ops'!$A$2:$A$401,$B$3) -> 0
A10: Total Covers | B10: =SUMIFS('Daily Ops'!$U$2:$U$401,'Daily Ops'!$A$2:$A$401,$B$3) -> 0
A11: Avg Check ($) | B11: =IF(N(B10)=0,"",N(B7)/N(B10))
A12: Food % of Net | B12: =IF(N(B7)=0,"",N(B8)/N(B7)) | C12: =Settings!$B$7 -> 0.6 | D12: =IF(C12="","",IF(ABS(N(B12)-N(C12))<=Settings!$B$9,"OK","OFF")) -> OFF
A13: Alcohol % of Net | B13: =IF(N(B7)=0,"",N(B9)/N(B7)) | C13: =Settings!$B$8 -> 0.4 | D13: =IF(C13="","",IF(ABS(N(B13)-N(C13))<=Settings!$B$9,"OK","OFF")) -> OFF
A14: Labor Cost ($) | B14: =SUMIFS('Daily Ops'!$Y$2:$Y$401,'Daily Ops'!$A$2:$A$401,$B$3) -> 0
A15: Labor % | B15: =IF(N(B7)=0,"",N(B14)/N(B7)) | C15: =Settings!$B$10 -> 0.25 | D15: =IF(C15="","",IF(N(B15)<=N(C15),"OK","HIGH")) -> OK
A16: Food COGS ($) | B16: =SUMIFS('Daily Ops'!$AA$2:$AA$401,'Daily Ops'!$A$2:$A$401,$B$3) -> 0
A17: Food Cost % | B17: =IF(N(B8)=0,"",N(B16)/N(B8)) | C17: =Settings!$B$11 -> 0.2 | D17: =IF(C17="","",IF(N(B17)<=N(C17),"OK","HIGH")) -> OK
A18: Liquor/Bev COGS ($) | B18: =SUMIFS('Daily Ops'!$AB$2:$AB$401,'Daily Ops'!$A$2:$A$401,$B$3) -> 0
A19: Liquor/Bev Cost % | B19: =IF(N(B9)=0,"",N(B18)/N(B9)) | C19: =Settings!$B$12 -> 0.15 | D19: =IF(C19="","",IF(N(B19)<=N(C19),"OK","HIGH")) -> OK
A20: Prime Cost % | B20: =IF(N(B7)=0,"",(N(B14)+N(B16)+N(B18))/N(B7)) | C20: =Settings!$B$13 -> 0.45 | D20: =IF(C20="","",IF(N(B20)<=N(C20),"OK","HIGH")) -> OK
A22: WTD / MTD Summary
A23: Period | B23: Net Sales ($) | C23: Food % | D23: Labor %
A24: WTD | B24: =IF($B$3="","",SUMIFS('Daily Ops'!$H$2:$H$401,'Daily Ops'!$A$2:$A$401,">="&$G$3,'Daily Ops'!$A$2:$A$401,"<="&$B$3)) -> 0 | C24: =IF(N(B24)=0,"",SUMIFS('Daily Ops'!$I$2:$I$401,'Daily Ops'!$A$2:$A$401,">="&$G$3,'Daily Ops'!$A$2:$A$401,"<="&$B$3)/N(B24)) | D24: =IF(N(B24)=0,"",SUMIFS('Daily Ops'!$Y$2:$Y$401,'Daily Ops'!$A$2:$A$401,">="&$G$3,'Daily Ops'!$A$2:$A$401,"<="&$B$3)/N(B24))
A25: MTD | B25: =IF($B$3="","",SUMIFS('Daily Ops'!$H$2:$H$401,'Daily Ops'!$A$2:$A$401,">="&$G$4,'Daily Ops'!$A$2:$A$401,"<="&$B$3)) -> 0 | C25: =IF(N(B25)=0,"",SUMIFS('Daily Ops'!$I$2:$I$401,'Daily Ops'!$A$2:$A$401,">="&$G$4,'Daily Ops'!$A$2:$A$401,"<="&$B$3)/N(B25)) | D25: =IF(N(B25)=0,"",SUMIFS('Daily Ops'!$Y$2:$Y$401,'Daily Ops'!$A$2:$A$401,">="&$G$4,'Daily Ops'!$A$2:$A$401,"<="&$B$3)/N(B25))

Sheet Daily Ops
A1: Date | B1: Day | C1: Opening Manager | D1: Closing Manager | E1: Notes | F1: Gross Sales ($) | G1: Discounts/Comps ($) | H1: Net Sales ($) | I1: Food Sales ($) | J1: Alcohol Sales ($) | K1: Non-Alc Sales ($) | L1: Sales Tax ($) | M1: Total Collected ($) | N1: Cash ($) | O1: Card ($) | P1: Other Payments ($) | Q1: Payments Total ($) | R1: Over/Short ($) | S1: Lunch Covers | T1: Dinner Covers | U1: Total Covers | V1: Avg Check ($) | W1: Food % of Net | X1: Alcohol % of Net | Y1: Labor Cost ($) | Z1: Labor % of Net | AA1: Food COGS ($) | AB1: Bev COGS ($) | AC1: Total COGS ($) | AD1: Food Cost % | AE1: Bev Cost % | AF1: Prime Cost ($) | AG1: Prime Cost % | AH1: Week Start | AI1: Month End | AJ1: Month Key
B2: =IF(A2="","",TEXT(A2,"ddd")) | H2: =IF(F2="","",F2-G2) | M2: =IF(H2="","",H2+L2) | Q2: =IF(A2="","",SUM(N2:P2)) | R2: =IF(A2="","",Q2-M2) | U2: =IF(A2="","",SUM(S2:T2)) | V2: =IF(U2=0,"",H2/U2) -> #DIV/0! | W2: =IF(H2=0,"",I2/H2) -> #DIV/0! | X2: =IF(H2=0,"",J2/H2) -> #DIV/0! | Y2: =IF(A2="","",SUMIFS('Labor Log'!$I$2:$I$2001,'Labor Log'!$A$2:$A$2001,A2)) | Z2: =IF(H2=0,"",Y2/H2) -> #DIV/0! | AA2: =IF(A2="","",SUMIFS('Inventory & COGS'!$H$2:$H$2001,'Inventory & COGS'!$A$2:$A$2001,A2,'Inventory & COGS'!$B$2:$B$2001,"Food")) | AB2: =IF(A2="","",SUMIFS('Inventory & COGS'!$H$2:$H$2001,'Inventory & COGS'!$A$2:$A$2001,A2,'Inventory & COGS'!$B$2:$B$2001,"Beverage")) | AC2: =IF(A2="","",AA2+AB2) | AD2: =IF(I2=0,"",AA2/I2) | AE2: =IF(J2=0,"",AB2/J2) | AF2: =IF(A2="","",Y2+AC2) | AG2: =IF(H2=0,"",AF2/H2) -> #DIV/0! | AH2: =IF(A2="","",A2-WEEKDAY(A2,2)+1) | AI2: =IF(A2="","",EOMONTH(A2,0)) | AJ2: =IF(A2="","",TEXT(A2,"yyyy-mm"))
B3: =IF(A3="","",TEXT(A3,"ddd")) | H3: =IF(F3="","",F3-G3) | M3: =IF(H3="","",H3+L3) | Q3: =IF(A3="","",SUM(N3:P3)) | R3: =IF(A3="","",Q3-M3) | U3: =IF(A3="","",SUM(S3:T3)) | V3: =IF(U3=0,"",H3/U3) -> #DIV/0! | W3: =IF(H3=0,"",I3/H3) -> #DIV/0! | X3: =IF(H3=0,"",J3/H3) -> #DIV/0! | Y3: =IF(A3="","",SUMIFS('Labor Log'!$I$2:$I$2001,'Labor Log'!$A$2:$A$2001,A3)) | Z3: =IF(H3=0,"",Y3/H3) -> #DIV/0! | AA3: =IF(A3="","",SUMIFS('Inventory & COGS'!$H$2:$H$2001,'Inventory & COGS'!$A$2:$A$2001,A3,'Inventory & COGS'!$B$2:$B$2001,"Food")) | AB3: =IF(A3="","",SUMIFS('Inventory & COGS'!$H$2:$H$2001,'Inventory & COGS'!$A$2:$A$2001,A3,'Inventory & COGS'!$B$2:$B$2001,"Beverage")) | AC3: =IF(A3="","",AA3+AB3) | AD3: =IF(I3=0,"",AA3/I3) | AE3: =IF(J3=0,"",AB3/J3) | AF3: =IF(A3="","",Y3+AC3) | AG3: =IF(H3=0,"",AF3/H3) -> #DIV/0! | AH3: =IF(A3="","",A3-WEEKDAY(A3,2)+1) | AI3: =IF(A3="","",EOMONTH(A3,0)) | AJ3: =IF(A3="","",TEXT(A3,"yyyy-mm"))
B4: =IF(A4="","",TEXT(A4,"ddd")) | H4: =IF(F4="","",F4-G4) | M4: =IF(H4="","",H4+L4) | Q4: =IF(A4="","",SUM(N4:P4)) | R4: =IF(A4="","",Q4-M4) | U4: =IF(A4="","",SUM(S4:T4)) | V4: =IF(U4=0,"",H4/U4) -> #DIV/0! | W4: =IF(H4=0,"",I4/H4) -> #DIV/0! | X4: =IF(H4=0,"",J4/H4) -> #DIV/0! | Y4: =IF(A4="","",SUMIFS('Labor Log'!$I$2:$I$2001,'Labor Log'!$A$2:$A$2001,A4)) | Z4: =IF(H4=0,"",Y4/H4) -> #DIV/0! | AA4: =IF(A4="","",SUMIFS('Inventory & COGS'!$H$2:$H$2001,'Inventory & COGS'!$A$2:$A$2001,A4,'Inventory & COGS'!$B$2:$B$2001,"Food")) | AB4: =IF(A4="","",SUMIFS('Inventory & COGS'!$H$2:$H$2001,'Inventory & COGS'!$A$2:$A$2001,A4,'Inventory & COGS'!$B$2:$B$2001,"Beverage")) | AC4: =IF(A4="","",AA4+AB4) | AD4: =IF(I4=0,"",AA4/I4) | AE4: =IF(J4=0,"",AB4/J4) | AF4: =IF(A4="","",Y4+AC4) | AG4: =IF(H4=0,"",AF4/H4) -> #DIV/0! | AH4: =IF(A4="","",A4-WEEKDAY(A4,2)+1) | AI4: =IF(A4="","",EOMONTH(A4,0)) | AJ4: =IF(A4="","",TEXT(A4,"yyyy-mm"))
B5: =IF(A5="","",TEXT(A5,"ddd")) | H5: =IF(F5="","",F5-G5) | M5: =IF(H5="","",H5+L5) | Q5: =IF(A5="","",SUM(N5:P5)) | R5: =IF(A5="","",Q5-M5) | U5: =IF(A5="","",SUM(S5:T5)) | V5: =IF(U5=0,"",H5/U5) -> #DIV/0! | W5: =IF(H5=0,"",I5/H5) -> #DIV/0! | X5: =IF(H5=0,"",J5/H5) -> #DIV/0! | Y5: =IF(A5="","",SUMIFS('Labor Log'!$I$2:$I$2001,'Labor Log'!$A$2:$A$2001,A5)) | Z5: =IF(H5=0,"",Y5/H5) -> #DIV/0! | AA5: =IF(A5="","",SUMIFS('Inventory & COGS'!$H$2:$H$2001,'Inventory & COGS'!$A$2:$A$2001,A5,'Inventory & COGS'!$B$2:$B$2001,"Food")) | AB5: =IF(A5="","",SUMIFS('Inventory & COGS'!$H$2:$H$2001,'Inventory & COGS'!$A$2:$A$2001,A5,'Inventory & COGS'!$B$2:$B$2001,"Beverage")) | AC5: =IF(A5="","",AA5+AB5) | AD5: =IF(I5=0,"",AA5/I5) | AE5: =IF(J5=0,"",AB5/J5) | AF5: =IF(A5="","",Y5+AC5) | AG5: =IF(H5=0,"",AF5/H5) -> #DIV/0! | AH5: =IF(A5="","",A5-WEEKDAY(A5,2)+1) | AI5: =IF(A5="","",EOMONTH(A5,0)) | AJ5: =IF(A5="","",TEXT(A5,"yyyy-mm"))
B6: =IF(A6="","",TEXT(A6,"ddd")) | H6: =IF(F6="","",F6-G6) | M6: =IF(H6="","",H6+L6) | Q6: =IF(A6="","",SUM(N6:P6)) | R6: =IF(A6="","",Q6-M6) | U6: =IF(A6="","",SUM(S6:T6)) | V6: =IF(U6=0,"",H6/U6) -> #DIV/0! | W6: =IF(H6=0,"",I6/H6) -> #DIV/0! | X6: =IF(H6=0,"",J6/H6) -> #DIV/0! | Y6: =IF(A6="","",SUMIFS('Labor Log'!$I$2:$I$2001,'Labor Log'!$A$2:$A$2001,A6)) | Z6: =IF(H6=0,"",Y6/H6) -> #DIV/0! | AA6: =IF(A6="","",SUMIFS('Inventory & COGS'!$H$2:$H$2001,'Inventory & COGS'!$A$2:$A$2001,A6,'Inventory & COGS'!$B$2:$B$2001,"Food")) | AB6: =IF(A6="","",SUMIFS('Inventory & COGS'!$H$2:$H$2001,'Inventory & COGS'!$A$2:$A$2001,A6,'Inventory & COGS'!$B$2:$B$2001,"Beverage")) | AC6: =IF(A6="","",AA6+AB6) | AD6: =IF(I6=0,"",AA6/I6) | AE6: =IF(J6=0,"",AB6/J6) | AF6: =IF(A6="","",Y6+AC6) | AG6: =IF(H6=0,"",AF6/H6) -> #DIV/0! | AH6: =IF(A6="","",A6-WEEKDAY(A6,2)+1) | AI6: =IF(A6="","",EOMONTH(A6,0)) | AJ6: =IF(A6="","",TEXT(A6,"yyyy-mm"))
B7: =IF(A7="","",TEXT(A7,"ddd")) | H7: =IF(F7="","",F7-G7) | M7: =IF(H7="","",H7+L7) | Q7: =IF(A7="","",SUM(N7:P7)) | R7: =IF(A7="","",Q7-M7) | U7: =IF(A7="","",SUM(S7:T7)) | V7: =IF(U7=0,"",H7/U7) -> #DIV/0! | W7: =IF(H7=0,"",I7/H7) -> #DIV/0! | X7: =IF(H7=0,"",J7/H7) -> #DIV/0! | Y7: =IF(A7="","",SUMIFS('Labor Log'!$I$2:$I$2001,'Labor Log'!$A$2:$A$2001,A7)) | Z7: =IF(H7=0,"",Y7/H7) -> #DIV/0! | AA7: =IF(A7="","",SUMIFS('Inventory & COGS'!$H$2:$H$2001,'Inventory & COGS'!$A$2:$A$2001,A7,'Inventory & COGS'!$B$2:$B$2001,"Food")) | AB7: =IF(A7="","",SUMIFS('Inventory & COGS'!$H$2:$H$2001,'Inventory & COGS'!$A$2:$A$2001,A7,'Inventory & COGS'!$B$2:$B$2001,"Beverage")) | AC7: =IF(A7="","",AA7+AB7) | AD7: =IF(I7=0,"",AA7/I7) | AE7: =IF(J7=0,"",AB7/J7) | AF7: =IF(A7="","",Y7+AC7) | AG7: =IF(H7=0,"",AF7/H7) -> #DIV/0! | AH7: =IF(A7="","",A7-WEEKDAY(A7,2)+1) | AI7: =IF(A7="","",EOMONTH(A7,0)) | AJ7: =IF(A7="","",TEXT(A7,"yyyy-mm"))
B8: =IF(A8="","",TEXT(A8,"ddd")) | H8: =IF(F8="","",F8-G8) | M8: =IF(H8="","",H8+L8) | Q8: =IF(A8="","",SUM(N8:P8)) | R8: =IF(A8="","",Q8-M8) | U8: =IF(A8="","",SUM(S8:T8)) | V8: =IF(U8=0,"",H8/U8) -> #DIV/0! | W8: =IF(H8=0,"",I8/H8) -> #DIV/0! | X8: =IF(H8=0,"",J8/H8) -> #DIV/0! | Y8: =IF(A8="","",SUMIFS('Labor Log'!$I$2:$I$2001,'Labor Log'!$A$2:$A$2001,A8)) | Z8: =IF(H8=0,"",Y8/H8) -> #DIV/0! | AA8: =IF(A8="","",SUMIFS('Inventory & COGS'!$H$2:$H$2001,'Inventory & COGS'!$A$2:$A$2001,A8,'Inventory & COGS'!$B$2:$B$2001,"Food")) | AB8: =IF(A8="","",SUMIFS('Inventory & COGS'!$H$2:$H$2001,'Inventory & COGS'!$A$2:$A$2001,A8,'Inventory & COGS'!$B$2:$B$2001,"Beverage")) | AC8: =IF(A8="","",AA8+AB8) | AD8: =IF(I8=0,"",AA8/I8) | AE8: =IF(J8=0,"",AB8/J8) | AF8: =IF(A8="","",Y8+AC8) | AG8: =IF(H8=0,"",AF8/H8) -> #DIV/0! | AH8: =IF(A8="","",A8-WEEKDAY(A8,2)+1) | AI8: =IF(A8="","",EOMONTH(A8,0)) | AJ8: =IF(A8="","",TEXT(A8,"yyyy-mm"))
B9: =IF(A9="","",TEXT(A9,"ddd")) | H9: =IF(F9="","",F9-G9) | M9: =IF(H9="","",H9+L9) | Q9: =IF(A9="","",SUM(N9:P9)) | R9: =IF(A9="","",Q9-M9) | U9: =IF(A9="","",SUM(S9:T9)) | V9: =IF(U9=0,"",H9/U9) -> #DIV/0! | W9: =IF(H9=0,"",I9/H9) -> #DIV/0! | X9: =IF(H9=0,"",J9/H9) -> #DIV/0! | Y9: =IF(A9="","",SUMIFS('Labor Log'!$I$2:$I$2001,'Labor Log'!$A$2:$A$2001,A9)) | Z9: =IF(H9=0,"",Y9/H9) -> #DIV/0! | AA9: =IF(A9="","",SUMIFS('Inventory & COGS'!$H$2:$H$2001,'Inventory & COGS'!$A$2:$A$2001,A9,'Inventory & COGS'!$B$2:$B$2001,"Food")) | AB9: =IF(A9="","",SUMIFS('Inventory & COGS'!$H$2:$H$2001,'Inventory & COGS'!$A$2:$A$2001,A9,'Inventory & COGS'!$B$2:$B$2001,"Beverage")) | AC9: =IF(A9="","",AA9+AB9) | AD9: =IF(I9=0,"",AA9/I9) | AE9: =IF(J9=0,"",AB9/J9) | AF9: =IF(A9="","",Y9+AC9) | AG9: =IF(H9=0,"",AF9/H9) -> #DIV/0! | AH9: =IF(A9="","",A9-WEEKDAY(A9,2)+1) | AI9: =IF(A9="","",EOMONTH(A9,0)) | AJ9: =IF(A9="","",TEXT(A9,"yyyy-mm"))
B10: =IF(A10="","",TEXT(A10,"ddd")) | H10: =IF(F10="","",F10-G10) | M10: =IF(H10="","",H10+L10) | Q10: =IF(A10="","",SUM(N10:P10)) | R10: =IF(A10="","",Q10-M10) | U10: =IF(A10="","",SUM(S10:T10)) | V10: =IF(U10=0,"",H10/U10) -> #DIV/0! | W10: =IF(H10=0,"",I10/H10) -> #DIV/0! | X10: =IF(H10=0,"",J10/H10) -> #DIV/0! | Y10: =IF(A10="","",SUMIFS('Labor Log'!$I$2:$I$2001,'Labor Log'!$A$2:$A$2001,A10)) | Z10: =IF(H10=0,"",Y10/H10) -> #DIV/0! | AA10: =IF(A10="","",SUMIFS('Inventory & COGS'!$H$2:$H$2001,'Inventory & COGS'!$A$2:$A$2001,A10,'Inventory & COGS'!$B$2:$B$2001,"Food")) | AB10: =IF(A10="","",SUMIFS('Inventory & COGS'!$H$2:$H$2001,'Inventory & COGS'!$A$2:$A$2001,A10,'Inventory & COGS'!$B$2:$B$2001,"Beverage")) | AC10: =IF(A10="","",AA10+AB10) | AD10: =IF(I10=0,"",AA10/I10) | AE10: =IF(J10=0,"",AB10/J10) | AF10: =IF(A10="","",Y10+AC10) | AG10: =IF(H10=0,"",AF10/H10) -> #DIV/0! | AH10: =IF(A10="","",A10-WEEKDAY(A10,2)+1) | AI10: =IF(A10="","",EOMONTH(A10,0)) | AJ10: =IF(A10="","",TEXT(A10,"yyyy-mm"))
B11: =IF(A11="","",TEXT(A11,"ddd")) | H11: =IF(F11="","",F11-G11) | M11: =IF(H11="","",H11+L11) | Q11: =IF(A11="","",SUM(N11:P11)) | R11: =IF(A11="","",Q11-M11) | U11: =IF(A11="","",SUM(S11:T11)) | V11: =IF(U11=0,"",H11/U11) -> #DIV/0! | W11: =IF(H11=0,"",I11/H11) -> #DIV/0! | X11: =IF(H11=0,"",J11/H11) -> #DIV/0! | Y11: =IF(A11="","",SUMIFS('Labor Log'!$I$2:$I$2001,'Labor Log'!$A$2:$A$2001,A11)) | Z11: =IF(H11=0,"",Y11/H11) -> #DIV/0! | AA11: =IF(A11="","",SUMIFS('Inventory & COGS'!$H$2:$H$2001,'Inventory & COGS'!$A$2:$A$2001,A11,'Inventory & COGS'!$B$2:$B$2001,"Food")) | AB11: =IF(A11="","",SUMIFS('Inventory & COGS'!$H$2:$H$2001,'Inventory & COGS'!$A$2:$A$2001,A11,'Inventory & COGS'!$B$2:$B$2001,"Beverage")) | AC11: =IF(A11="","",AA11+AB11) | AD11: =IF(I11=0,"",AA11/I11) | AE11: =IF(J11=0,"",AB11/J11) | AF11: =IF(A11="","",Y11+AC11) | AG11: =IF(H11=0,"",AF11/H11) -> #DIV/0! | AH11: =IF(A11="","",A11-WEEKDAY(A11,2)+1) | AI11: =IF(A11="","",EOMONTH(A11,0)) | AJ11: =IF(A11="","",TEXT(A11,"yyyy-mm"))
B12: =IF(A12="","",TEXT(A12,"ddd")) | H12: =IF(F12="","",F12-G12) | M12: =IF(H12="","",H12+L12) | Q12: =IF(A12="","",SUM(N12:P12)) | R12: =IF(A12="","",Q12-M12) | U12: =IF(A12="","",SUM(S12:T12)) | V12: =IF(U12=0,"",H12/U12) -> #DIV/0! | W12: =IF(H12=0,"",I12/H12) -> #DIV/0! | X12: =IF(H12=0,"",J12/H12) -> #DIV/0! | Y12: =IF(A12="","",SUMIFS('Labor Log'!$I$2:$I$2001,'Labor Log'!$A$2:$A$2001,A12)) | Z12: =IF(H12=0,"",Y12/H12) -> #DIV/0! | AA12: =IF(A12="","",SUMIFS('Inventory & COGS'!$H$2:$H$2001,'Inventory & COGS'!$A$2:$A$2001,A12,'Inventory & COGS'!$B$2:$B$2001,"Food")) | AB12: =IF(A12="","",SUMIFS('Inventory & COGS'!$H$2:$H$2001,'Inventory & COGS'!$A$2:$A$2001,A12,'Inventory & COGS'!$B$2:$B$2001,"Beverage")) | AC12: =IF(A12="","",AA12+AB12) | AD12: =IF(I12=0,"",AA12/I12) | AE12: =IF(J12=0,"",AB12/J12) | AF12: =IF(A12="","",Y12+AC12) | AG12: =IF(H12=0,"",AF12/H12) -> #DIV/0! | AH12: =IF(A12="","",A12-WEEKDAY(A12,2)+1) | AI12: =IF(A12="","",EOMONTH(A12,0)) | AJ12: =IF(A12="","",TEXT(A12,"yyyy-mm"))
B13: =IF(A13="","",TEXT(A13,"ddd")) | H13: =IF(F13="","",F13-G13) | M13: =IF(H13="","",H13+L13) | Q13: =IF(A13="","",SUM(N13:P13)) | R13: =IF(A13="","",Q13-M13) | U13: =IF(A13="","",SUM(S13:T13)) | V13: =IF(U13=0,"",H13/U13) -> #DIV/0! | W13: =IF(H13=0,"",I13/H13) -> #DIV/0! | X13: =IF(H13=0,"",J13/H13) -> #DIV/0! | Y13: =IF(A13="","",SUMIFS('Labor Log'!$I$2:$I$2001,'Labor Log'!$A$2:$A$2001,A13)) | Z13: =IF(H13=0,"",Y13/H13) -> #DIV/0! | AA13: =IF(A13="","",SUMIFS('Inventory & COGS'!$H$2:$H$2001,'Inventory & COGS'!$A$2:$A$2001,A13,'Inventory & COGS'!$B$2:$B$2001,"Food")) | AB13: =IF(A13="","",SUMIFS('Inventory & COGS'!$H$2:$H$2001,'Inventory & COGS'!$A$2:$A$2001,A13,'Inventory & COGS'!$B$2:$B$2001,"Beverage")) | AC13: =IF(A13="","",AA13+AB13) | AD13: =IF(I13=0,"",AA13/I13) | AE13: =IF(J13=0,"",AB13/J13) | AF13: =IF(A13="","",Y13+AC13) | AG13: =IF(H13=0,"",AF13/H13) -> #DIV/0! | AH13: =IF(A13="","",A13-WEEKDAY(A13,2)+1) | AI13: =IF(A13="","",EOMONTH(A13,0)) | AJ13: =IF(A13="","",TEXT(A13,"yyyy-mm"))
... B401: =IF(A401="","",TEXT(A401,"ddd")) | H401: =IF(F401="","",F401-G401) | M401: =IF(H401="","",H401+L401) | Q401: =IF(A401="","",SUM(N401:P401)) | R401: =IF(A401="","",Q401-M401) | U401: =IF(A401="","",SUM(S401:T401)) | V401: =IF(U401=0,"",H401/U401) -> #DIV/0! | W401: =IF(H401=0,"",I401/H401) -> #DIV/0! | X401: =IF(H401=0,"",J401/H401) -> #DIV/0! | Y401: =IF(A401="","",SUMIFS('Labor Log'!$I$2:$I$2001,'Labor Log'!$A$2:$A$2001,A401)) | Z401: =IF(H401=0,"",Y401/H401) -> #DIV/0! | AA401: =IF(A401="","",SUMIFS('Inventory & COGS'!$H$2:$H$2001,'Inventory & COGS'!$A$2:$A$2001,A401,'Inventory & COGS'!$B$2:$B$2001,"Food")) | AB401: =IF(A401="","",SUMIFS('Inventory & COGS'!$H$2:$H$2001,'Inventory & COGS'!$A$2:$A$2001,A401,'Inventory & COGS'!$B$2:$B$2001,"Beverage")) | AC401: =IF(A401="","",AA401+AB401) | AD401: =IF(I401=0,"",AA401/I401) | AE401: =IF(J401=0,"",AB401/J401) | AF401: =IF(A401="","",Y401+AC401) | AG401: =IF(H401=0,"",AF401/H401) -> #DIV/0! | AH401: =IF(A401="","",A401-WEEKDAY(A401,2)+1) | AI401: =IF(A401="","",EOMONTH(A401,0)) | AJ401: =IF(A401="","",TEXT(A401,"yyyy-mm"))

Sheet Labor Log
A1: Date | B1: Employee | C1: Role (FOH/BOH) | D1: In Time | E1: Out Time | F1: Break (hrs) | G1: Hours | H1: Hourly Rate ($) | I1: Labor Cost ($) | J1: Notes
G2: 12 | I2: =IF(OR(G2="",H2=""),"",G2*H2)
G3: =IF(OR(D3="",E3=""),"",((IF(E3<D3,E3+1,E3)-D3)*24)-IF(F3="",0,F3)) | I3: =IF(OR(G3="",H3=""),"",G3*H3)
G4: =IF(OR(D4="",E4=""),"",((IF(E4<D4,E4+1,E4)-D4)*24)-IF(F4="",0,F4)) | I4: =IF(OR(G4="",H4=""),"",G4*H4)
G5: =IF(OR(D5="",E5=""),"",((IF(E5<D5,E5+1,E5)-D5)*24)-IF(F5="",0,F5)) | I5: =IF(OR(G5="",H5=""),"",G5*H5)
G6: =IF(OR(D6="",E6=""),"",((IF(E6<D6,E6+1,E6)-D6)*24)-IF(F6="",0,F6)) | I6: =IF(OR(G6="",H6=""),"",G6*H6)
G7: =IF(OR(D7="",E7=""),"",((IF(E7<D7,E7+1,E7)-D7)*24)-IF(F7="",0,F7)) | I7: =IF(OR(G7="",H7=""),"",G7*H7)
G8: =IF(OR(D8="",E8=""),"",((IF(E8<D8,E8+1,E8)-D8)*24)-IF(F8="",0,F8)) | I8: =IF(OR(G8="",H8=""),"",G8*H8)
G9: =IF(OR(D9="",E9=""),"",((IF(E9<D9,E9+1,E9)-D9)*24)-IF(F9="",0,F9)) | I9: =IF(OR(G9="",H9=""),"",G9*H9)
G10: =IF(OR(D10="",E10=""),"",((IF(E10<D10,E10+1,E10)-D10)*24)-IF(F10="",0,F10)) | I10: =IF(OR(G10="",H10=""),"",G10*H10)
G11: =IF(OR(D11="",E11=""),"",((IF(E11<D11,E11+1,E11)-D11)*24)-IF(F11="",0,F11)) | I11: =IF(OR(G11="",H11=""),"",G11*H11)
G12: =IF(OR(D12="",E12=""),"",((IF(E12<D12,E12+1,E12)-D12)*24)-IF(F12="",0,F12)) | I12: =IF(OR(G12="",H12=""),"",G12*H12)
G13: =IF(OR(D13="",E13=""),"",((IF(E13<D13,E13+1,E13)-D13)*24)-IF(F13="",0,F13)) | I13: =IF(OR(G13="",H13=""),"",G13*H13)
G14: =IF(OR(D14="",E14=""),"",((IF(E14<D14,E14+1,E14)-D14)*24)-IF(F14="",0,F14)) | I14: =IF(OR(G14="",H14=""),"",G14*H14)
... G2001: =IF(OR(D2001="",E2001=""),"",((IF(E2001<D2001,E2001+1,E2001)-D2001)*24)-IF(F2001="",0,F2001)) | I2001: =IF(OR(G2001="",H2001=""),"",G2001*H2001)

Sheet Inventory & COGS
A1: Date | B1: Type (Food/Beverage) | C1: Category | D1: Item | E1: Vendor | F1: Qty Used | G1: Unit Cost ($) | H1: Cost Used ($) | I1: Notes
H2: =IF(OR(F2="",G2=""),"",F2*G2)
H3: =IF(OR(F3="",G3=""),"",F3*G3)
H4: =IF(OR(F4="",G4=""),"",F4*G4)
H5: =IF(OR(F5="",G5=""),"",F5*G5)
H6: =IF(OR(F6="",G6=""),"",F6*G6)
H7: =IF(OR(F7="",G7=""),"",F7*G7)
H8: =IF(OR(F8="",G8=""),"",F8*G8)
H9: =IF(OR(F9="",G9=""),"",F9*G9)
H10: =IF(OR(F10="",G10=""),"",F10*G10)
H11: =IF(OR(F11="",G11=""),"",F11*G11)
H12: =IF(OR(F12="",G12=""),"",F12*G12)
H13: =IF(OR(F13="",G13=""),"",F13*G13)
... H2001: =IF(OR(F2001="",G2001=""),"",F2001*G2001)

Sheet Cash Control
A1: Date | B1: Opening Cash ($) | C1: Cash Sales ($) | D1: Paid Outs ($) | E1: Deposits ($) | F1: Closing Cash Count ($) | G1: Expected Closing ($) | H1: Over/Short ($) | I1: Notes
C2: =IF(A2="","",SUMIFS('Daily Ops'!$N$2:$N$401,'Daily Ops'!$A$2:$A$401,A2)) | G2: =IF(A2="","",B2+C2-D2-E2) | H2: =IF(A2="","",F2-G2)
C3: =IF(A3="","",SUMIFS('Daily Ops'!$N$2:$N$401,'Daily Ops'!$A$2:$A$401,A3)) | G3: =IF(A3="","",B3+C3-D3-E3) | H3: =IF(A3="","",F3-G3)
C4: =IF(A4="","",SUMIFS('Daily Ops'!$N$2:$N$401,'Daily Ops'!$A$2:$A$401,A4)) | G4: =IF(A4="","",B4+C4-D4-E4) | H4: =IF(A4="","",F4-G4)
C5: =IF(A5="","",SUMIFS('Daily Ops'!$N$2:$N$401,'Daily Ops'!$A$2:$A$401,A5)) | G5: =IF(A5="","",B5+C5-D5-E5) | H5: =IF(A5="","",F5-G5)
C6: =IF(A6="","",SUMIFS('Daily Ops'!$N$2:$N$401,'Daily Ops'!$A$2:$A$401,A6)) | G6: =IF(A6="","",B6+C6-D6-E6) | H6: =IF(A6="","",F6-G6)
C7: =IF(A7="","",SUMIFS('Daily Ops'!$N$2:$N$401,'Daily Ops'!$A$2:$A$401,A7)) | G7: =IF(A7="","",B7+C7-D7-E7) | H7: =IF(A7="","",F7-G7)
C8: =IF(A8="","",SUMIFS('Daily Ops'!$N$2:$N$401,'Daily Ops'!$A$2:$A$401,A8)) | G8: =IF(A8="","",B8+C8-D8-E8) | H8: =IF(A8="","",F8-G8)
C9: =IF(A9="","",SUMIFS('Daily Ops'!$N$2:$N$401,'Daily Ops'!$A$2:$A$401,A9)) | G9: =IF(A9="","",B9+C9-D9-E9) | H9: =IF(A9="","",F9-G9)
C10: =IF(A10="","",SUMIFS('Daily Ops'!$N$2:$N$401,'Daily Ops'!$A$2:$A$401,A10)) | G10: =IF(A10="","",B10+C10-D10-E10) | H10: =IF(A10="","",F10-G10)
C11: =IF(A11="","",SUMIFS('Daily Ops'!$N$2:$N$401,'Daily Ops'!$A$2:$A$401,A11)) | G11: =IF(A11="","",B11+C11-D11-E11) | H11: =IF(A11="","",F11-G11)
C12: =IF(A12="","",SUMIFS('Daily Ops'!$N$2:$N$401,'Daily Ops'!$A$2:$A$401,A12)) | G12: =IF(A12="","",B12+C12-D12-E12) | H12: =IF(A12="","",F12-G12)
C13: =IF(A13="","",SUMIFS('Daily Ops'!$N$2:$N$401,'Daily Ops'!$A$2:$A$401,A13)) | G13: =IF(A13="","",B13+C13-D13-E13) | H13: =IF(A13="","",F13-G13)
... C401: =IF(A401="","",SUMIFS('Daily Ops'!$N$2:$N$401,'Daily Ops'!$A$2:$A$401,A401)) | G401: =IF(A401="","",B401+C401-D401-E401) | H401: =IF(A401="","",F401-G401)

Sheet Issues Log
A1: Date | B1: Issue Type | C1: Description | D1: Action Taken | E1: Responsible | F1: Resolved (Y/N)

Sheet Weekly Rollup
A1: Week Start | B1: Week End | C1: Net Sales ($) | D1: Food Sales ($) | E1: Alcohol Sales ($) | F1: Total Covers | G1: Labor Cost ($) | H1: Food COGS ($) | I1: Bev COGS ($) | J1: Total COGS ($) | K1: Avg Check ($) | L1: Labor % | M1: Food % | N1: Alcohol % | O1: Prime Cost ($) | P1: Prime Cost %
A2: =Settings!$B$5 -> 46023 | B2: =A2+6 -> 46029 | C2: =SUMIFS('Daily Ops'!$H$2:$H$401,'Daily Ops'!$AH$2:$AH$401,$A2) -> 0 | D2: =SUMIFS('Daily Ops'!$I$2:$I$401,'Daily Ops'!$AH$2:$AH$401,$A2) -> 0 | E2: =SUMIFS('Daily Ops'!$J$2:$J$401,'Daily Ops'!$AH$2:$AH$401,$A2) -> 0 | F2: =SUMIFS('Daily Ops'!$U$2:$U$401,'Daily Ops'!$AH$2:$AH$401,$A2) -> 0 | G2: =SUMIFS('Daily Ops'!$Y$2:$Y$401,'Daily Ops'!$AH$2:$AH$401,$A2) -> 0 | H2: =SUMIFS('Daily Ops'!$AA$2:$AA$401,'Daily Ops'!$AH$2:$AH$401,$A2) -> 0 | I2: =SUMIFS('Daily Ops'!$AB$2:$AB$401,'Daily Ops'!$AH$2:$AH$401,$A2) -> 0 | J2: =H2+I2 -> 0 | K2: =IF(F2=0,"",C2/F2) | L2: =IF(C2=0,"",G2/C2) | M2: =IF(C2=0,"",D2/C2) | N2: =IF(C2=0,"",E2/C2) | O2: =G2+J2 -> 0 | P2: =IF(C2=0,"",O2/C2)
A3: =A2+7 -> 46030 | B3: =A3+6 -> 46036 | C3: =SUMIFS('Daily Ops'!$H$2:$H$401,'Daily Ops'!$AH$2:$AH$401,$A3) -> 0 | D3: =SUMIFS('Daily Ops'!$I$2:$I$401,'Daily Ops'!$AH$2:$AH$401,$A3) -> 0 | E3: =SUMIFS('Daily Ops'!$J$2:$J$401,'Daily Ops'!$AH$2:$AH$401,$A3) -> 0 | F3: =SUMIFS('Daily Ops'!$U$2:$U$401,'Daily Ops'!$AH$2:$AH$401,$A3) -> 0 | G3: =SUMIFS('Daily Ops'!$Y$2:$Y$401,'Daily Ops'!$AH$2:$AH$401,$A3) -> 0 | H3: =SUMIFS('Daily Ops'!$AA$2:$AA$401,'Daily Ops'!$AH$2:$AH$401,$A3) -> 0 | I3: =SUMIFS('Daily Ops'!$AB$2:$AB$401,'Daily Ops'!$AH$2:$AH$401,$A3) -> 0 | J3: =H3+I3 -> 0 | K3: =IF(F3=0,"",C3/F3) | L3: =IF(C3=0,"",G3/C3) | M3: =IF(C3=0,"",D3/C3) | N3: =IF(C3=0,"",E3/C3) | O3: =G3+J3 -> 0 | P3: =IF(C3=0,"",O3/C3)
A4: =A3+7 -> 46037 | B4: =A4+6 -> 46043 | C4: =SUMIFS('Daily Ops'!$H$2:$H$401,'Daily Ops'!$AH$2:$AH$401,$A4) -> 0 | D4: =SUMIFS('Daily Ops'!$I$2:$I$401,'Daily Ops'!$AH$2:$AH$401,$A4) -> 0 | E4: =SUMIFS('Daily Ops'!$J$2:$J$401,'Daily Ops'!$AH$2:$AH$401,$A4) -> 0 | F4: =SUMIFS('Daily Ops'!$U$2:$U$401,'Daily Ops'!$AH$2:$AH$401,$A4) -> 0 | G4: =SUMIFS('Daily Ops'!$Y$2:$Y$401,'Daily Ops'!$AH$2:$AH$401,$A4) -> 0 | H4: =SUMIFS('Daily Ops'!$AA$2:$AA$401,'Daily Ops'!$AH$2:$AH$401,$A4) -> 0 | I4: =SUMIFS('Daily Ops'!$AB$2:$AB$401,'Daily Ops'!$AH$2:$AH$401,$A4) -> 0 | J4: =H4+I4 -> 0 | K4: =IF(F4=0,"",C4/F4) | L4: =IF(C4=0,"",G4/C4) | M4: =IF(C4=0,"",D4/C4) | N4: =IF(C4=0,"",E4/C4) | O4: =G4+J4 -> 0 | P4: =IF(C4=0,"",O4/C4)
A5: =A4+7 -> 46044 | B5: =A5+6 -> 46050 | C5: =SUMIFS('Daily Ops'!$H$2:$H$401,'Daily Ops'!$AH$2:$AH$401,$A5) -> 0 | D5: =SUMIFS('Daily Ops'!$I$2:$I$401,'Daily Ops'!$AH$2:$AH$401,$A5) -> 0 | E5: =SUMIFS('Daily Ops'!$J$2:$J$401,'Daily Ops'!$AH$2:$AH$401,$A5) -> 0 | F5: =SUMIFS('Daily Ops'!$U$2:$U$401,'Daily Ops'!$AH$2:$AH$401,$A5) -> 0 | G5: =SUMIFS('Daily Ops'!$Y$2:$Y$401,'Daily Ops'!$AH$2:$AH$401,$A5) -> 0 | H5: =SUMIFS('Daily Ops'!$AA$2:$AA$401,'Daily Ops'!$AH$2:$AH$401,$A5) -> 0 | I5: =SUMIFS('Daily Ops'!$AB$2:$AB$401,'Daily Ops'!$AH$2:$AH$401,$A5) -> 0 | J5: =H5+I5 -> 0 | K5: =IF(F5=0,"",C5/F5) | L5: =IF(C5=0,"",G5/C5) | M5: =IF(C5=0,"",D5/C5) | N5: =IF(C5=0,"",E5/C5) | O5: =G5+J5 -> 0 | P5: =IF(C5=0,"",O5/C5)
A6: =A5+7 -> 46051 | B6: =A6+6 -> 46057 | C6: =SUMIFS('Daily Ops'!$H$2:$H$401,'Daily Ops'!$AH$2:$AH$401,$A6) -> 0 | D6: =SUMIFS('Daily Ops'!$I$2:$I$401,'Daily Ops'!$AH$2:$AH$401,$A6) -> 0 | E6: =SUMIFS('Daily Ops'!$J$2:$J$401,'Daily Ops'!$AH$2:$AH$401,$A6) -> 0 | F6: =SUMIFS('Daily Ops'!$U$2:$U$401,'Daily Ops'!$AH$2:$AH$401,$A6) -> 0 | G6: =SUMIFS('Daily Ops'!$Y$2:$Y$401,'Daily Ops'!$AH$2:$AH$401,$A6) -> 0 | H6: =SUMIFS('Daily Ops'!$AA$2:$AA$401,'Daily Ops'!$AH$2:$AH$401,$A6) -> 0 | I6: =SUMIFS('Daily Ops'!$AB$2:$AB$401,'Daily Ops'!$AH$2:$AH$401,$A6) -> 0 | J6: =H6+I6 -> 0 | K6: =IF(F6=0,"",C6/F6) | L6: =IF(C6=0,"",G6/C6) | M6: =IF(C6=0,"",D6/C6) | N6: =IF(C6=0,"",E6/C6) | O6: =G6+J6 -> 0 | P6: =IF(C6=0,"",O6/C6)
A7: =A6+7 -> 46058 | B7: =A7+6 -> 46064 | C7: =SUMIFS('Daily Ops'!$H$2:$H$401,'Daily Ops'!$AH$2:$AH$401,$A7) -> 0 | D7: =SUMIFS('Daily Ops'!$I$2:$I$401,'Daily Ops'!$AH$2:$AH$401,$A7) -> 0 | E7: =SUMIFS('Daily Ops'!$J$2:$J$401,'Daily Ops'!$AH$2:$AH$401,$A7) -> 0 | F7: =SUMIFS('Daily Ops'!$U$2:$U$401,'Daily Ops'!$AH$2:$AH$401,$A7) -> 0 | G7: =SUMIFS('Daily Ops'!$Y$2:$Y$401,'Daily Ops'!$AH$2:$AH$401,$A7) -> 0 | H7: =SUMIFS('Daily Ops'!$AA$2:$AA$401,'Daily Ops'!$AH$2:$AH$401,$A7) -> 0 | I7: =SUMIFS('Daily Ops'!$AB$2:$AB$401,'Daily Ops'!$AH$2:$AH$401,$A7) -> 0 | J7: =H7+I7 -> 0 | K7: =IF(F7=0,"",C7/F7) | L7: =IF(C7=0,"",G7/C7) | M7: =IF(C7=0,"",D7/C7) | N7: =IF(C7=0,"",E7/C7) | O7: =G7+J7 -> 0 | P7: =IF(C7=0,"",O7/C7)
A8: =A7+7 -> 46065 | B8: =A8+6 -> 46071 | C8: =SUMIFS('Daily Ops'!$H$2:$H$401,'Daily Ops'!$AH$2:$AH$401,$A8) -> 0 | D8: =SUMIFS('Daily Ops'!$I$2:$I$401,'Daily Ops'!$AH$2:$AH$401,$A8) -> 0 | E8: =SUMIFS('Daily Ops'!$J$2:$J$401,'Daily Ops'!$AH$2:$AH$401,$A8) -> 0 | F8: =SUMIFS('Daily Ops'!$U$2:$U$401,'Daily Ops'!$AH$2:$AH$401,$A8) -> 0 | G8: =SUMIFS('Daily Ops'!$Y$2:$Y$401,'Daily Ops'!$AH$2:$AH$401,$A8) -> 0 | H8: =SUMIFS('Daily Ops'!$AA$2:$AA$401,'Daily Ops'!$AH$2:$AH$401,$A8) -> 0 | I8: =SUMIFS('Daily Ops'!$AB$2:$AB$401,'Daily Ops'!$AH$2:$AH$401,$A8) -> 0 | J8: =H8+I8 -> 0 | K8: =IF(F8=0,"",C8/F8) | L8: =IF(C8=0,"",G8/C8) | M8: =IF(C8=0,"",D8/C8) | N8: =IF(C8=0,"",E8/C8) | O8: =G8+J8 -> 0 | P8: =IF(C8=0,"",O8/C8)
A9: =A8+7 -> 46072 | B9: =A9+6 -> 46078 | C9: =SUMIFS('Daily Ops'!$H$2:$H$401,'Daily Ops'!$AH$2:$AH$401,$A9) -> 0 | D9: =SUMIFS('Daily Ops'!$I$2:$I$401,'Daily Ops'!$AH$2:$AH$401,$A9) -> 0 | E9: =SUMIFS('Daily Ops'!$J$2:$J$401,'Daily Ops'!$AH$2:$AH$401,$A9) -> 0 | F9: =SUMIFS('Daily Ops'!$U$2:$U$401,'Daily Ops'!$AH$2:$AH$401,$A9) -> 0 | G9: =SUMIFS('Daily Ops'!$Y$2:$Y$401,'Daily Ops'!$AH$2:$AH$401,$A9) -> 0 | H9: =SUMIFS('Daily Ops'!$AA$2:$AA$401,'Daily Ops'!$AH$2:$AH$401,$A9) -> 0 | I9: =SUMIFS('Daily Ops'!$AB$2:$AB$401,'Daily Ops'!$AH$2:$AH$401,$A9) -> 0 | J9: =H9+I9 -> 0 | K9: =IF(F9=0,"",C9/F9) | L9: =IF(C9=0,"",G9/C9) | M9: =IF(C9=0,"",D9/C9) | N9: =IF(C9=0,"",E9/C9) | O9: =G9+J9 -> 0 | P9: =IF(C9=0,"",O9/C9)
A10: =A9+7 -> 46079 | B10: =A10+6 -> 46085 | C10: =SUMIFS('Daily Ops'!$H$2:$H$401,'Daily Ops'!$AH$2:$AH$401,$A10) -> 0 | D10: =SUMIFS('Daily Ops'!$I$2:$I$401,'Daily Ops'!$AH$2:$AH$401,$A10) -> 0 | E10: =SUMIFS('Daily Ops'!$J$2:$J$401,'Daily Ops'!$AH$2:$AH$401,$A10) -> 0 | F10: =SUMIFS('Daily Ops'!$U$2:$U$401,'Daily Ops'!$AH$2:$AH$401,$A10) -> 0 | G10: =SUMIFS('Daily Ops'!$Y$2:$Y$401,'Daily Ops'!$AH$2:$AH$401,$A10) -> 0 | H10: =SUMIFS('Daily Ops'!$AA$2:$AA$401,'Daily Ops'!$AH$2:$AH$401,$A10) -> 0 | I10: =SUMIFS('Daily Ops'!$AB$2:$AB$401,'Daily Ops'!$AH$2:$AH$401,$A10) -> 0 | J10: =H10+I10 -> 0 | K10: =IF(F10=0,"",C10/F10) | L10: =IF(C10=0,"",G10/C10) | M10: =IF(C10=0,"",D10/C10) | N10: =IF(C10=0,"",E10/C10) | O10: =G10+J10 -> 0 | P10: =IF(C10=0,"",O10/C10)
A11: =A10+7 -> 46086 | B11: =A11+6 -> 46092 | C11: =SUMIFS('Daily Ops'!$H$2:$H$401,'Daily Ops'!$AH$2:$AH$401,$A11) -> 0 | D11: =SUMIFS('Daily Ops'!$I$2:$I$401,'Daily Ops'!$AH$2:$AH$401,$A11) -> 0 | E11: =SUMIFS('Daily Ops'!$J$2:$J$401,'Daily Ops'!$AH$2:$AH$401,$A11) -> 0 | F11: =SUMIFS('Daily Ops'!$U$2:$U$401,'Daily Ops'!$AH$2:$AH$401,$A11) -> 0 | G11: =SUMIFS('Daily Ops'!$Y$2:$Y$401,'Daily Ops'!$AH$2:$AH$401,$A11) -> 0 | H11: =SUMIFS('Daily Ops'!$AA$2:$AA$401,'Daily Ops'!$AH$2:$AH$401,$A11) -> 0 | I11: =SUMIFS('Daily Ops'!$AB$2:$AB$401,'Daily Ops'!$AH$2:$AH$401,$A11) -> 0 | J11: =H11+I11 -> 0 | K11: =IF(F11=0,"",C11/F11) | L11: =IF(C11=0,"",G11/C11) | M11: =IF(C11=0,"",D11/C11) | N11: =IF(C11=0,"",E11/C11) | O11: =G11+J11 -> 0 | P11: =IF(C11=0,"",O11/C11)
A12: =A11+7 -> 46093 | B12: =A12+6 -> 46099 | C12: =SUMIFS('Daily Ops'!$H$2:$H$401,'Daily Ops'!$AH$2:$AH$401,$A12) -> 0 | D12: =SUMIFS('Daily Ops'!$I$2:$I$401,'Daily Ops'!$AH$2:$AH$401,$A12) -> 0 | E12: =SUMIFS('Daily Ops'!$J$2:$J$401,'Daily Ops'!$AH$2:$AH$401,$A12) -> 0 | F12: =SUMIFS('Daily Ops'!$U$2:$U$401,'Daily Ops'!$AH$2:$AH$401,$A12) -> 0 | G12: =SUMIFS('Daily Ops'!$Y$2:$Y$401,'Daily Ops'!$AH$2:$AH$401,$A12) -> 0 | H12: =SUMIFS('Daily Ops'!$AA$2:$AA$401,'Daily Ops'!$AH$2:$AH$401,$A12) -> 0 | I12: =SUMIFS('Daily Ops'!$AB$2:$AB$401,'Daily Ops'!$AH$2:$AH$401,$A12) -> 0 | J12: =H12+I12 -> 0 | K12: =IF(F12=0,"",C12/F12) | L12: =IF(C12=0,"",G12/C12) | M12: =IF(C12=0,"",D12/C12) | N12: =IF(C12=0,"",E12/C12) | O12: =G12+J12 -> 0 | P12: =IF(C12=0,"",O12/C12)
A13: =A12+7 -> 46100 | B13: =A13+6 -> 46106 | C13: =SUMIFS('Daily Ops'!$H$2:$H$401,'Daily Ops'!$AH$2:$AH$401,$A13) -> 0 | D13: =SUMIFS('Daily Ops'!$I$2:$I$401,'Daily Ops'!$AH$2:$AH$401,$A13) -> 0 | E13: =SUMIFS('Daily Ops'!$J$2:$J$401,'Daily Ops'!$AH$2:$AH$401,$A13) -> 0 | F13: =SUMIFS('Daily Ops'!$U$2:$U$401,'Daily Ops'!$AH$2:$AH$401,$A13) -> 0 | G13: =SUMIFS('Daily Ops'!$Y$2:$Y$401,'Daily Ops'!$AH$2:$AH$401,$A13) -> 0 | H13: =SUMIFS('Daily Ops'!$AA$2:$AA$401,'Daily Ops'!$AH$2:$AH$401,$A13) -> 0 | I13: =SUMIFS('Daily Ops'!$AB$2:$AB$401,'Daily Ops'!$AH$2:$AH$401,$A13) -> 0 | J13: =H13+I13 -> 0 | K13: =IF(F13=0,"",C13/F13) | L13: =IF(C13=0,"",G13/C13) | M13: =IF(C13=0,"",D13/C13) | N13: =IF(C13=0,"",E13/C13) | O13: =G13+J13 -> 0 | P13: =IF(C13=0,"",O13/C13)
A14: =A13+7 -> 46107 | B14: =A14+6 -> 46113 | C14: =SUMIFS('Daily Ops'!$H$2:$H$401,'Daily Ops'!$AH$2:$AH$401,$A14) -> 0 | D14: =SUMIFS('Daily Ops'!$I$2:$I$401,'Daily Ops'!$AH$2:$AH$401,$A14) -> 0 | E14: =SUMIFS('Daily Ops'!$J$2:$J$401,'Daily Ops'!$AH$2:$AH$401,$A14) -> 0 | F14: =SUMIFS('Daily Ops'!$U$2:$U$401,'Daily Ops'!$AH$2:$AH$401,$A14) -> 0 | G14: =SUMIFS('Daily Ops'!$Y$2:$Y$401,'Daily Ops'!$AH$2:$AH$401,$A14) -> 0 | H14: =SUMIFS('Daily Ops'!$AA$2:$AA$401,'Daily Ops'!$AH$2:$AH$401,$A14) -> 0 | I14: =SUMIFS('Daily Ops'!$AB$2:$AB$401,'Daily Ops'!$AH$2:$AH$401,$A14) -> 0 | J14: =H14+I14 -> 0 | K14: =IF(F14=0,"",C14/F14) | L14: =IF(C14=0,"",G14/C14) | M14: =IF(C14=0,"",D14/C14) | N14: =IF(C14=0,"",E14/C14) | O14: =G14+J14 -> 0 | P14: =IF(C14=0,"",O14/C14)
... A61: =A60+7 -> 46436 | B61: =A61+6 -> 46442 | C61: =SUMIFS('Daily Ops'!$H$2:$H$401,'Daily Ops'!$AH$2:$AH$401,$A61) -> 0 | D61: =SUMIFS('Daily Ops'!$I$2:$I$401,'Daily Ops'!$AH$2:$AH$401,$A61) -> 0 | E61: =SUMIFS('Daily Ops'!$J$2:$J$401,'Daily Ops'!$AH$2:$AH$401,$A61) -> 0 | F61: =SUMIFS('Daily Ops'!$U$2:$U$401,'Daily Ops'!$AH$2:$AH$401,$A61) -> 0 | G61: =SUMIFS('Daily Ops'!$Y$2:$Y$401,'Daily Ops'!$AH$2:$AH$401,$A61) -> 0 | H61: =SUMIFS('Daily Ops'!$AA$2:$AA$401,'Daily Ops'!$AH$2:$AH$401,$A61) -> 0 | I61: =SUMIFS('Daily Ops'!$AB$2:$AB$401,'Daily Ops'!$AH$2:$AH$401,$A61) -> 0 | J61: =H61+I61 -> 0 | K61: =IF(F61=0,"",C61/F61) | L61: =IF(C61=0,"",G61/C61) | M61: =IF(C61=0,"",D61/C61) | N61: =IF(C61=0,"",E61/C61) | O61: =G61+J61 -> 0 | P61: =IF(C61=0,"",O61/C61)

Sheet Monthly Rollup
A1: Month | B1: Month Key | C1: Net Sales ($) | D1: Food Sales ($) | E1: Alcohol Sales ($) | F1: Total Covers | G1: Labor Cost ($) | H1: Food COGS ($) | I1: Bev COGS ($) | J1: Total COGS ($) | K1: Avg Check ($) | L1: Labor % | M1: Food % | N1: Alcohol % | O1: Prime Cost ($) | P1: Prime Cost %
A2: =Settings!$B$6 -> 46023 | B2: =TEXT(A2,"yyyy-mm") -> 2026-01 | C2: =SUMIFS('Daily Ops'!$H$2:$H$401,'Daily Ops'!$AJ$2:$AJ$401,$B2) -> 0 | D2: =SUMIFS('Daily Ops'!$I$2:$I$401,'Daily Ops'!$AJ$2:$AJ$401,$B2) -> 0 | E2: =SUMIFS('Daily Ops'!$J$2:$J$401,'Daily Ops'!$AJ$2:$AJ$401,$B2) -> 0 | F2: =SUMIFS('Daily Ops'!$U$2:$U$401,'Daily Ops'!$AJ$2:$AJ$401,$B2) -> 0 | G2: =SUMIFS('Daily Ops'!$Y$2:$Y$401,'Daily Ops'!$AJ$2:$AJ$401,$B2) -> 0 | H2: =SUMIFS('Daily Ops'!$AA$2:$AA$401,'Daily Ops'!$AJ$2:$AJ$401,$B2) -> 0 | I2: =SUMIFS('Daily Ops'!$AB$2:$AB$401,'Daily Ops'!$AJ$2:$AJ$401,$B2) -> 0 | J2: =H2+I2 -> 0 | K2: =IF(F2=0,"",C2/F2) | L2: =IF(C2=0,"",G2/C2) | M2: =IF(C2=0,"",D2/C2) | N2: =IF(C2=0,"",E2/C2) | O2: =G2+J2 -> 0 | P2: =IF(C2=0,"",O2/C2)
A3: =EDATE(A2,1) -> 46054 | B3: =TEXT(A3,"yyyy-mm") -> 2026-02 | C3: =SUMIFS('Daily Ops'!$H$2:$H$401,'Daily Ops'!$AJ$2:$AJ$401,$B3) -> 0 | D3: =SUMIFS('Daily Ops'!$I$2:$I$401,'Daily Ops'!$AJ$2:$AJ$401,$B3) -> 0 | E3: =SUMIFS('Daily Ops'!$J$2:$J$401,'Daily Ops'!$AJ$2:$AJ$401,$B3) -> 0 | F3: =SUMIFS('Daily Ops'!$U$2:$U$401,'Daily Ops'!$AJ$2:$AJ$401,$B3) -> 0 | G3: =SUMIFS('Daily Ops'!$Y$2:$Y$401,'Daily Ops'!$AJ$2:$AJ$401,$B3) -> 0 | H3: =SUMIFS('Daily Ops'!$AA$2:$AA$401,'Daily Ops'!$AJ$2:$AJ$401,$B3) -> 0 | I3: =SUMIFS('Daily Ops'!$AB$2:$AB$401,'Daily Ops'!$AJ$2:$AJ$401,$B3) -> 0 | J3: =H3+I3 -> 0 | K3: =IF(F3=0,"",C3/F3) | L3: =IF(C3=0,"",G3/C3) | M3: =IF(C3=0,"",D3/C3) | N3: =IF(C3=0,"",E3/C3) | O3: =G3+J3 -> 0 | P3: =IF(C3=0,"",O3/C3)
A4: =EDATE(A3,1) -> 46082 | B4: =TEXT(A4,"yyyy-mm") -> 2026-03 | C4: =SUMIFS('Daily Ops'!$H$2:$H$401,'Daily Ops'!$AJ$2:$AJ$401,$B4) -> 0 | D4: =SUMIFS('Daily Ops'!$I$2:$I$401,'Daily Ops'!$AJ$2:$AJ$401,$B4) -> 0 | E4: =SUMIFS('Daily Ops'!$J$2:$J$401,'Daily Ops'!$AJ$2:$AJ$401,$B4) -> 0 | F4: =SUMIFS('Daily Ops'!$U$2:$U$401,'Daily Ops'!$AJ$2:$AJ$401,$B4) -> 0 | G4: =SUMIFS('Daily Ops'!$Y$2:$Y$401,'Daily Ops'!$AJ$2:$AJ$401,$B4) -> 0 | H4: =SUMIFS('Daily Ops'!$AA$2:$AA$401,'Daily Ops'!$AJ$2:$AJ$401,$B4) -> 0 | I4: =SUMIFS('Daily Ops'!$AB$2:$AB$401,'Daily Ops'!$AJ$2:$AJ$401,$B4) -> 0 | J4: =H4+I4 -> 0 | K4: =IF(F4=0,"",C4/F4) | L4: =IF(C4=0,"",G4/C4) | M4: =IF(C4=0,"",D4/C4) | N4: =IF(C4=0,"",E4/C4) | O4: =G4+J4 -> 0 | P4: =IF(C4=0,"",O4/C4)
A5: =EDATE(A4,1) -> 46113 | B5: =TEXT(A5,"yyyy-mm") -> 2026-04 | C5: =SUMIFS('Daily Ops'!$H$2:$H$401,'Daily Ops'!$AJ$2:$AJ$401,$B5) -> 0 | D5: =SUMIFS('Daily Ops'!$I$2:$I$401,'Daily Ops'!$AJ$2:$AJ$401,$B5) -> 0 | E5: =SUMIFS('Daily Ops'!$J$2:$J$401,'Daily Ops'!$AJ$2:$AJ$401,$B5) -> 0 | F5: =SUMIFS('Daily Ops'!$U$2:$U$401,'Daily Ops'!$AJ$2:$AJ$401,$B5) -> 0 | G5: =SUMIFS('Daily Ops'!$Y$2:$Y$401,'Daily Ops'!$AJ$2:$AJ$401,$B5) -> 0 | H5: =SUMIFS('Daily Ops'!$AA$2:$AA$401,'Daily Ops'!$AJ$2:$AJ$401,$B5) -> 0 | I5: =SUMIFS('Daily Ops'!$AB$2:$AB$401,'Daily Ops'!$AJ$2:$AJ$401,$B5) -> 0 | J5: =H5+I5 -> 0 | K5: =IF(F5=0,"",C5/F5) | L5: =IF(C5=0,"",G5/C5) | M5: =IF(C5=0,"",D5/C5) | N5: =IF(C5=0,"",E5/C5) | O5: =G5+J5 -> 0 | P5: =IF(C5=0,"",O5/C5)
A6: =EDATE(A5,1) -> 46143 | B6: =TEXT(A6,"yyyy-mm") -> 2026-05 | C6: =SUMIFS('Daily Ops'!$H$2:$H$401,'Daily Ops'!$AJ$2:$AJ$401,$B6) -> 0 | D6: =SUMIFS('Daily Ops'!$I$2:$I$401,'Daily Ops'!$AJ$2:$AJ$401,$B6) -> 0 | E6: =SUMIFS('Daily Ops'!$J$2:$J$401,'Daily Ops'!$AJ$2:$AJ$401,$B6) -> 0 | F6: =SUMIFS('Daily Ops'!$U$2:$U$401,'Daily Ops'!$AJ$2:$AJ$401,$B6) -> 0 | G6: =SUMIFS('Daily Ops'!$Y$2:$Y$401,'Daily Ops'!$AJ$2:$AJ$401,$B6) -> 0 | H6: =SUMIFS('Daily Ops'!$AA$2:$AA$401,'Daily Ops'!$AJ$2:$AJ$401,$B6) -> 0 | I6: =SUMIFS('Daily Ops'!$AB$2:$AB$401,'Daily Ops'!$AJ$2:$AJ$401,$B6) -> 0 | J6: =H6+I6 -> 0 | K6: =IF(F6=0,"",C6/F6) | L6: =IF(C6=0,"",G6/C6) | M6: =IF(C6=0,"",D6/C6) | N6: =IF(C6=0,"",E6/C6) | O6: =G6+J6 -> 0 | P6: =IF(C6=0,"",O6/C6)
A7: =EDATE(A6,1) -> 46174 | B7: =TEXT(A7,"yyyy-mm") -> 2026-06 | C7: =SUMIFS('Daily Ops'!$H$2:$H$401,'Daily Ops'!$AJ$2:$AJ$401,$B7) -> 0 | D7: =SUMIFS('Daily Ops'!$I$2:$I$401,'Daily Ops'!$AJ$2:$AJ$401,$B7) -> 0 | E7: =SUMIFS('Daily Ops'!$J$2:$J$401,'Daily Ops'!$AJ$2:$AJ$401,$B7) -> 0 | F7: =SUMIFS('Daily Ops'!$U$2:$U$401,'Daily Ops'!$AJ$2:$AJ$401,$B7) -> 0 | G7: =SUMIFS('Daily Ops'!$Y$2:$Y$401,'Daily Ops'!$AJ$2:$AJ$401,$B7) -> 0 | H7: =SUMIFS('Daily Ops'!$AA$2:$AA$401,'Daily Ops'!$AJ$2:$AJ$401,$B7) -> 0 | I7: =SUMIFS('Daily Ops'!$AB$2:$AB$401,'Daily Ops'!$AJ$2:$AJ$401,$B7) -> 0 | J7: =H7+I7 -> 0 | K7: =IF(F7=0,"",C7/F7) | L7: =IF(C7=0,"",G7/C7) | M7: =IF(C7=0,"",D7/C7) | N7: =IF(C7=0,"",E7/C7) | O7: =G7+J7 -> 0 | P7: =IF(C7=0,"",O7/C7)
A8: =EDATE(A7,1) -> 46204 | B8: =TEXT(A8,"yyyy-mm") -> 2026-07 | C8: =SUMIFS('Daily Ops'!$H$2:$H$401,'Daily Ops'!$AJ$2:$AJ$401,$B8) -> 0 | D8: =SUMIFS('Daily Ops'!$I$2:$I$401,'Daily Ops'!$AJ$2:$AJ$401,$B8) -> 0 | E8: =SUMIFS('Daily Ops'!$J$2:$J$401,'Daily Ops'!$AJ$2:$AJ$401,$B8) -> 0 | F8: =SUMIFS('Daily Ops'!$U$2:$U$401,'Daily Ops'!$AJ$2:$AJ$401,$B8) -> 0 | G8: =SUMIFS('Daily Ops'!$Y$2:$Y$401,'Daily Ops'!$AJ$2:$AJ$401,$B8) -> 0 | H8: =SUMIFS('Daily Ops'!$AA$2:$AA$401,'Daily Ops'!$AJ$2:$AJ$401,$B8) -> 0 | I8: =SUMIFS('Daily Ops'!$AB$2:$AB$401,'Daily Ops'!$AJ$2:$AJ$401,$B8) -> 0 | J8: =H8+I8 -> 0 | K8: =IF(F8=0,"",C8/F8) | L8: =IF(C8=0,"",G8/C8) | M8: =IF(C8=0,"",D8/C8) | N8: =IF(C8=0,"",E8/C8) | O8: =G8+J8 -> 0 | P8: =IF(C8=0,"",O8/C8)
A9: =EDATE(A8,1) -> 46235 | B9: =TEXT(A9,"yyyy-mm") -> 2026-08 | C9: =SUMIFS('Daily Ops'!$H$2:$H$401,'Daily Ops'!$AJ$2:$AJ$401,$B9) -> 0 | D9: =SUMIFS('Daily Ops'!$I$2:$I$401,'Daily Ops'!$AJ$2:$AJ$401,$B9) -> 0 | E9: =SUMIFS('Daily Ops'!$J$2:$J$401,'Daily Ops'!$AJ$2:$AJ$401,$B9) -> 0 | F9: =SUMIFS('Daily Ops'!$U$2:$U$401,'Daily Ops'!$AJ$2:$AJ$401,$B9) -> 0 | G9: =SUMIFS('Daily Ops'!$Y$2:$Y$401,'Daily Ops'!$AJ$2:$AJ$401,$B9) -> 0 | H9: =SUMIFS('Daily Ops'!$AA$2:$AA$401,'Daily Ops'!$AJ$2:$AJ$401,$B9) -> 0 | I9: =SUMIFS('Daily Ops'!$AB$2:$AB$401,'Daily Ops'!$AJ$2:$AJ$401,$B9) -> 0 | J9: =H9+I9 -> 0 | K9: =IF(F9=0,"",C9/F9) | L9: =IF(C9=0,"",G9/C9) | M9: =IF(C9=0,"",D9/C9) | N9: =IF(C9=0,"",E9/C9) | O9: =G9+J9 -> 0 | P9: =IF(C9=0,"",O9/C9)
A10: =EDATE(A9,1) -> 46266 | B10: =TEXT(A10,"yyyy-mm") -> 2026-09 | C10: =SUMIFS('Daily Ops'!$H$2:$H$401,'Daily Ops'!$AJ$2:$AJ$401,$B10) -> 0 | D10: =SUMIFS('Daily Ops'!$I$2:$I$401,'Daily Ops'!$AJ$2:$AJ$401,$B10) -> 0 | E10: =SUMIFS('Daily Ops'!$J$2:$J$401,'Daily Ops'!$AJ$2:$AJ$401,$B10) -> 0 | F10: =SUMIFS('Daily Ops'!$U$2:$U$401,'Daily Ops'!$AJ$2:$AJ$401,$B10) -> 0 | G10: =SUMIFS('Daily Ops'!$Y$2:$Y$401,'Daily Ops'!$AJ$2:$AJ$401,$B10) -> 0 | H10: =SUMIFS('Daily Ops'!$AA$2:$AA$401,'Daily Ops'!$AJ$2:$AJ$401,$B10) -> 0 | I10: =SUMIFS('Daily Ops'!$AB$2:$AB$401,'Daily Ops'!$AJ$2:$AJ$401,$B10) -> 0 | J10: =H10+I10 -> 0 | K10: =IF(F10=0,"",C10/F10) | L10: =IF(C10=0,"",G10/C10) | M10: =IF(C10=0,"",D10/C10) | N10: =IF(C10=0,"",E10/C10) | O10: =G10+J10 -> 0 | P10: =IF(C10=0,"",O10/C10)
A11: =EDATE(A10,1) -> 46296 | B11: =TEXT(A11,"yyyy-mm") -> 2026-10 | C11: =SUMIFS('Daily Ops'!$H$2:$H$401,'Daily Ops'!$AJ$2:$AJ$401,$B11) -> 0 | D11: =SUMIFS('Daily Ops'!$I$2:$I$401,'Daily Ops'!$AJ$2:$AJ$401,$B11) -> 0 | E11: =SUMIFS('Daily Ops'!$J$2:$J$401,'Daily Ops'!$AJ$2:$AJ$401,$B11) -> 0 | F11: =SUMIFS('Daily Ops'!$U$2:$U$401,'Daily Ops'!$AJ$2:$AJ$401,$B11) -> 0 | G11: =SUMIFS('Daily Ops'!$Y$2:$Y$401,'Daily Ops'!$AJ$2:$AJ$401,$B11) -> 0 | H11: =SUMIFS('Daily Ops'!$AA$2:$AA$401,'Daily Ops'!$AJ$2:$AJ$401,$B11) -> 0 | I11: =SUMIFS('Daily Ops'!$AB$2:$AB$401,'Daily Ops'!$AJ$2:$AJ$401,$B11) -> 0 | J11: =H11+I11 -> 0 | K11: =IF(F11=0,"",C11/F11) | L11: =IF(C11=0,"",G11/C11) | M11: =IF(C11=0,"",D11/C11) | N11: =IF(C11=0,"",E11/C11) | O11: =G11+J11 -> 0 | P11: =IF(C11=0,"",O11/C11)
A12: =EDATE(A11,1) -> 46327 | B12: =TEXT(A12,"yyyy-mm") -> 2026-11 | C12: =SUMIFS('Daily Ops'!$H$2:$H$401,'Daily Ops'!$AJ$2:$AJ$401,$B12) -> 0 | D12: =SUMIFS('Daily Ops'!$I$2:$I$401,'Daily Ops'!$AJ$2:$AJ$401,$B12) -> 0 | E12: =SUMIFS('Daily Ops'!$J$2:$J$401,'Daily Ops'!$AJ$2:$AJ$401,$B12) -> 0 | F12: =SUMIFS('Daily Ops'!$U$2:$U$401,'Daily Ops'!$AJ$2:$AJ$401,$B12) -> 0 | G12: =SUMIFS('Daily Ops'!$Y$2:$Y$401,'Daily Ops'!$AJ$2:$AJ$401,$B12) -> 0 | H12: =SUMIFS('Daily Ops'!$AA$2:$AA$401,'Daily Ops'!$AJ$2:$AJ$401,$B12) -> 0 | I12: =SUMIFS('Daily Ops'!$AB$2:$AB$401,'Daily Ops'!$AJ$2:$AJ$401,$B12) -> 0 | J12: =H12+I12 -> 0 | K12: =IF(F12=0,"",C12/F12) | L12: =IF(C12=0,"",G12/C12) | M12: =IF(C12=0,"",D12/C12) | N12: =IF(C12=0,"",E12/C12) | O12: =G12+J12 -> 0 | P12: =IF(C12=0,"",O12/C12)
A13: =EDATE(A12,1) -> 46357 | B13: =TEXT(A13,"yyyy-mm") -> 2026-12 | C13: =SUMIFS('Daily Ops'!$H$2:$H$401,'Daily Ops'!$AJ$2:$AJ$401,$B13) -> 0 | D13: =SUMIFS('Daily Ops'!$I$2:$I$401,'Daily Ops'!$AJ$2:$AJ$401,$B13) -> 0 | E13: =SUMIFS('Daily Ops'!$J$2:$J$401,'Daily Ops'!$AJ$2:$AJ$401,$B13) -> 0 | F13: =SUMIFS('Daily Ops'!$U$2:$U$401,'Daily Ops'!$AJ$2:$AJ$401,$B13) -> 0 | G13: =SUMIFS('Daily Ops'!$Y$2:$Y$401,'Daily Ops'!$AJ$2:$AJ$401,$B13) -> 0 | H13: =SUMIFS('Daily Ops'!$AA$2:$AA$401,'Daily Ops'!$AJ$2:$AJ$401,$B13) -> 0 | I13: =SUMIFS('Daily Ops'!$AB$2:$AB$401,'Daily Ops'!$AJ$2:$AJ$401,$B13) -> 0 | J13: =H13+I13 -> 0 | K13: =IF(F13=0,"",C13/F13) | L13: =IF(C13=0,"",G13/C13) | M13: =IF(C13=0,"",D13/C13) | N13: =IF(C13=0,"",E13/C13) | O13: =G13+J13 -> 0 | P13: =IF(C13=0,"",O13/C13)
A14: =EDATE(A13,1) -> 46388 | B14: =TEXT(A14,"yyyy-mm") -> 2027-01 | C14: =SUMIFS('Daily Ops'!$H$2:$H$401,'Daily Ops'!$AJ$2:$AJ$401,$B14) -> 0 | D14: =SUMIFS('Daily Ops'!$I$2:$I$401,'Daily Ops'!$AJ$2:$AJ$401,$B14) -> 0 | E14: =SUMIFS('Daily Ops'!$J$2:$J$401,'Daily Ops'!$AJ$2:$AJ$401,$B14) -> 0 | F14: =SUMIFS('Daily Ops'!$U$2:$U$401,'Daily Ops'!$AJ$2:$AJ$401,$B14) -> 0 | G14: =SUMIFS('Daily Ops'!$Y$2:$Y$401,'Daily Ops'!$AJ$2:$AJ$401,$B14) -> 0 | H14: =SUMIFS('Daily Ops'!$AA$2:$AA$401,'Daily Ops'!$AJ$2:$AJ$401,$B14) -> 0 | I14: =SUMIFS('Daily Ops'!$AB$2:$AB$401,'Daily Ops'!$AJ$2:$AJ$401,$B14) -> 0 | J14: =H14+I14 -> 0 | K14: =IF(F14=0,"",C14/F14) | L14: =IF(C14=0,"",G14/C14) | M14: =IF(C14=0,"",D14/C14) | N14: =IF(C14=0,"",E14/C14) | O14: =G14+J14 -> 0 | P14: =IF(C14=0,"",O14/C14)
... A25: =EDATE(A24,1) -> 46722 | B25: =TEXT(A25,"yyyy-mm") -> 2027-12 | C25: =SUMIFS('Daily Ops'!$H$2:$H$401,'Daily Ops'!$AJ$2:$AJ$401,$B25) -> 0 | D25: =SUMIFS('Daily Ops'!$I$2:$I$401,'Daily Ops'!$AJ$2:$AJ$401,$B25) -> 0 | E25: =SUMIFS('Daily Ops'!$J$2:$J$401,'Daily Ops'!$AJ$2:$AJ$401,$B25) -> 0 | F25: =SUMIFS('Daily Ops'!$U$2:$U$401,'Daily Ops'!$AJ$2:$AJ$401,$B25) -> 0 | G25: =SUMIFS('Daily Ops'!$Y$2:$Y$401,'Daily Ops'!$AJ$2:$AJ$401,$B25) -> 0 | H25: =SUMIFS('Daily Ops'!$AA$2:$AA$401,'Daily Ops'!$AJ$2:$AJ$401,$B25) -> 0 | I25: =SUMIFS('Daily Ops'!$AB$2:$AB$401,'Daily Ops'!$AJ$2:$AJ$401,$B25) -> 0 | J25: =H25+I25 -> 0 | K25: =IF(F25=0,"",C25/F25) | L25: =IF(C25=0,"",G25/C25) | M25: =IF(C25=0,"",D25/C25) | N25: =IF(C25=0,"",E25/C25) | O25: =G25+J25 -> 0 | P25: =IF(C25=0,"",O25/C25)

Sheet Settings
A1: Restaurant Ops Template — Settings
A3: Setting | B3: Value | C3: Notes
A4: Model version | B4: v1.0 (Excel/Google Sheets compatible)
A5: Start Date (for rollups) | B5: 46023 | C5: Weekly Rollup starts here (one row per week).
A6: Start Month (first day) | B6: 46023 | C6: Monthly Rollup starts here (one row per month).
A7: Food sales mix target | B7: 0.6 | C7: Target: 60% of Net Sales
A8: Alcohol sales mix target | B8: 0.4 | C8: Target: 40% of Net Sales
A9: Mix tolerance (±) | B9: 0.03 | C9: Dashboard flags mix as OFF if outside tolerance.
A10: Labor % target | B10: 0.25 | C10: Target labor cost as % of Net Sales
A11: Food cost % target | B11: 0.2 | C11: Target food cost as % of Food Sales
A12: Liquor/Bev cost % target | B12: 0.15 | C12: Target liquor/beverage cost as % of Alcohol Sales
A13: Prime cost % target | B13: 0.45 | C13: Prime cost target = Labor + Food COGS + Bev COGS as % of Net Sales (editable)
A14: Sales tax rate (optional) | B14: 0 | C14: If you want, enter your tax rate and manually use it for Sales Tax.
